{
  "$schema": "https://json-schema.org/draft/2020-12/schema",
  "title": "ISO 8601-1:2019 Ordinal Date (Extended Format)",
  "description": "A complete representation of an ordinal date in extended format [YYYY][\"-\"][DDD] where DDD is the calendar day of year (001-365/366) (ยง5.2.3.1 b)",
  "examples": [ "1985-102", "2000-001", "2000-366", "2023-365", "0000-001" ],
  "x-license": "https://github.com/sourcemeta/std/blob/main/LICENSE",
  "x-links": [ "https://www.iso.org/standard/70907.html" ],
  "type": "string",
  "pattern": "^[0-9]{4}-(00[1-9]|0[1-9][0-9]|[12][0-9][0-9]|3[0-5][0-9]|36[0-6])$"
}
