{
  "$schema": "https://json-schema.org/draft/2020-12/schema",
  "title": "ISO 4217 Numeric Currency Code (Historical)",
  "description": "A three-digit numeric withdrawn currency code, excluding funds and precious metals (2025-03-31)",
  "examples": [ 4, 8, 20, 24 ],
  "deprecated": true,
  "x-license": "https://github.com/sourcemeta/std/blob/main/LICENSE",
  "x-links": [ "https://www.iso.org/iso-4217-currency-codes.html" ],
  "anyOf": [
    {
      "title": "Afghani",
      "x-country-name": "AFGHANISTAN",
      "x-withdrawal-date": "2003-01",
      "const": 4
    },
    {
      "title": "Old Lek",
      "x-country-name": "ALBANIA",
      "x-withdrawal-date": "1989-12",
      "const": 8
    },
    {
      "title": "Andorran Peseta",
      "x-country-name": "ANDORRA",
      "x-withdrawal-date": "2003-07",
      "const": 20
    },
    {
      "title": "New Kwanza",
      "x-country-name": "ANGOLA",
      "x-withdrawal-date": "2000-02",
      "const": 24
    },
    {
      "title": "Azerbaijanian Manat",
      "x-country-name": "AZERBAIJAN",
      "x-withdrawal-date": "2005-12",
      "const": 31
    },
    {
      "title": "Peso",
      "x-country-name": "ARGENTINA",
      "x-withdrawal-date": "1989 to 1990",
      "const": 32
    },
    {
      "title": "Schilling",
      "x-country-name": "AUSTRIA",
      "x-withdrawal-date": "2002-03",
      "const": 40
    },
    {
      "title": "Belgian Franc",
      "x-country-name": "BELGIUM",
      "x-withdrawal-date": "2002-03",
      "const": 56
    },
    {
      "title": "Peso boliviano",
      "x-country-name": "BOLIVIA",
      "x-withdrawal-date": "1987-02",
      "const": 68
    },
    {
      "title": "Dinar",
      "x-country-name": "BOSNIA AND HERZEGOVINA",
      "x-withdrawal-date": "1998-07",
      "const": 70
    },
    {
      "title": "New Cruzado",
      "x-country-name": "BRAZIL",
      "x-withdrawal-date": "1990-03",
      "const": 76
    },
    {
      "title": "Lev",
      "x-country-name": "BULGARIA",
      "x-withdrawal-date": "2003-11",
      "const": 100
    },
    {
      "title": "Kyat",
      "x-country-name": "BURMA",
      "x-withdrawal-date": "1990-02",
      "const": 104
    },
    {
      "title": "Belarusian Ruble",
      "x-country-name": "BELARUS",
      "x-withdrawal-date": "2001-01",
      "const": 112
    },
    {
      "title": "Zaire",
      "x-country-name": "ZAIRE",
      "x-withdrawal-date": "1994-02",
      "const": 180
    },
    {
      "title": "Kuna",
      "x-country-name": "CROATIA",
      "x-withdrawal-date": "2023-01",
      "const": 191
    },
    {
      "title": "Cyprus Pound",
      "x-country-name": "CYPRUS",
      "x-withdrawal-date": "2008-01",
      "const": 196
    },
    {
      "title": "Koruna",
      "x-country-name": "CZECHOSLOVAKIA",
      "x-withdrawal-date": "1993-03",
      "const": 200
    },
    {
      "title": "Krona A/53",
      "x-country-name": "CZECHOSLOVAKIA",
      "x-withdrawal-date": "1989 to 1990",
      "const": 203
    },
    {
      "title": "Sucre",
      "x-country-name": "ECUADOR",
      "x-withdrawal-date": "2000-09",
      "const": 218
    },
    {
      "title": "Ekwele",
      "x-country-name": "EQUATORIAL GUINEA",
      "x-withdrawal-date": "1986-06",
      "const": 226
    },
    {
      "title": "Kroon",
      "x-country-name": "ESTONIA",
      "x-withdrawal-date": "2011-01",
      "const": 233
    },
    {
      "title": "Markka",
      "x-country-name": "FINLAND",
      "x-withdrawal-date": "2002-03",
      "const": 246
    },
    {
      "title": "French Franc",
      "x-country-name": "SAINT-BARTHÉLEMY",
      "x-withdrawal-date": "1999-01",
      "const": 250
    },
    {
      "title": "Georgian Coupon",
      "x-country-name": "GEORGIA",
      "x-withdrawal-date": "1995-10",
      "const": 268
    },
    {
      "title": "Deutsche Mark",
      "x-country-name": "GERMANY",
      "x-withdrawal-date": "2002-03",
      "const": 276
    },
    {
      "title": "Mark der DDR",
      "x-country-name": "GERMAN DEMOCRATIC REPUBLIC",
      "x-withdrawal-date": "1990-07 to 1990-09",
      "const": 278
    },
    {
      "title": "Cedi",
      "x-country-name": "GHANA",
      "x-withdrawal-date": "2008-01",
      "const": 288
    },
    {
      "title": "Drachma",
      "x-country-name": "GREECE",
      "x-withdrawal-date": "2002-03",
      "const": 300
    },
    {
      "title": "Syli",
      "x-country-name": "GUINEA",
      "x-withdrawal-date": "1986-02",
      "const": 324
    },
    {
      "title": "Old Krona",
      "x-country-name": "ICELAND",
      "x-withdrawal-date": "1989 to 1990",
      "const": 352
    },
    {
      "title": "Rupiah",
      "x-country-name": "TIMOR-LESTE",
      "x-withdrawal-date": "2002-07",
      "const": 360
    },
    {
      "title": "Irish Pound",
      "x-country-name": "IRELAND",
      "x-withdrawal-date": "2002-03",
      "const": 372
    },
    {
      "title": "Old Shekel",
      "x-country-name": "ISRAEL",
      "x-withdrawal-date": "1989 to 1990",
      "const": 376
    },
    {
      "title": "Italian Lira",
      "x-country-name": "SAN MARINO",
      "x-withdrawal-date": "2002-03",
      "const": 380
    },
    {
      "title": "Pathet Lao Kip",
      "x-country-name": "LAO",
      "x-withdrawal-date": "1979-12",
      "const": 418
    },
    {
      "title": "Loti",
      "x-country-name": "LESOTHO",
      "x-withdrawal-date": "1985-05",
      "const": 426
    },
    {
      "title": "Latvian Ruble",
      "x-country-name": "LATVIA",
      "x-withdrawal-date": "1994-12",
      "const": 428
    },
    {
      "title": "Talonas",
      "x-country-name": "LITHUANIA",
      "x-withdrawal-date": "1993-07",
      "const": 440
    },
    {
      "title": "Luxembourg Franc",
      "x-country-name": "LUXEMBOURG",
      "x-withdrawal-date": "2002-03",
      "const": 442
    },
    {
      "title": "Malagasy Franc",
      "x-country-name": "MADAGASCAR",
      "x-withdrawal-date": "2004-12",
      "const": 450
    },
    {
      "title": "Kwacha",
      "x-country-name": "MALAWI",
      "x-withdrawal-date": "2016-02",
      "const": 454
    },
    {
      "title": "Maldive Rupee",
      "x-country-name": "MALDIVES",
      "x-withdrawal-date": "1989-12",
      "const": 462
    },
    {
      "title": "Mali Franc",
      "x-country-name": "MALI",
      "x-withdrawal-date": "1984-11",
      "const": 466
    },
    {
      "title": "Maltese Pound",
      "x-country-name": "MALTA",
      "x-withdrawal-date": "1983-06",
      "const": 470
    },
    {
      "title": "Ouguiya",
      "x-country-name": "MAURITANIA",
      "x-withdrawal-date": "2017-12",
      "const": 478
    },
    {
      "title": "Mexican Peso",
      "x-country-name": "MEXICO",
      "x-withdrawal-date": "1993-01",
      "const": 484
    },
    {
      "title": "Mozambique Metical",
      "x-country-name": "MOZAMBIQUE",
      "x-withdrawal-date": "2006-06",
      "const": 508
    },
    {
      "title": "Netherlands Guilder",
      "x-country-name": "NETHERLANDS",
      "x-withdrawal-date": "2002-03",
      "const": 528
    },
    {
      "title": "Netherlands Antillean Guilder",
      "x-country-name": "SINT MAARTEN (DUTCH PART)",
      "x-withdrawal-date": "2025-03",
      "const": 532
    },
    {
      "title": "Cordoba",
      "x-country-name": "NICARAGUA",
      "x-withdrawal-date": "1990-10",
      "const": 558
    },
    {
      "title": "Sol",
      "x-country-name": "PERU",
      "x-withdrawal-date": "1986-02",
      "const": 604
    },
    {
      "title": "Zloty",
      "x-country-name": "POLAND",
      "x-withdrawal-date": "1997-01",
      "const": 616
    },
    {
      "title": "Portuguese Escudo",
      "x-country-name": "PORTUGAL",
      "x-withdrawal-date": "2002-03",
      "const": 620
    },
    {
      "title": "Guinea-Bissau Peso",
      "x-country-name": "GUINEA-BISSAU",
      "x-withdrawal-date": "1997-05",
      "const": 624
    },
    {
      "title": "Timor Escudo",
      "x-country-name": "TIMOR-LESTE",
      "x-withdrawal-date": "2002-11",
      "const": 626
    },
    {
      "title": "Old Leu",
      "x-country-name": "ROMANIA",
      "x-withdrawal-date": "2005-06",
      "const": 642
    },
    {
      "title": "Dobra",
      "x-country-name": "SAO TOME AND PRINCIPE",
      "x-withdrawal-date": "2017-12",
      "const": 678
    },
    {
      "title": "Leone",
      "x-country-name": "SIERRA LEONE",
      "x-withdrawal-date": "2023-12",
      "const": 694
    },
    {
      "title": "Slovak Koruna",
      "x-country-name": "SLOVAKIA",
      "x-withdrawal-date": "2009-01",
      "const": 703
    },
    {
      "title": "Old Dong",
      "x-country-name": "VIETNAM",
      "x-withdrawal-date": "1989-1990",
      "const": 704
    },
    {
      "title": "Tolar",
      "x-country-name": "SLOVENIA",
      "x-withdrawal-date": "2007-01",
      "const": 705
    },
    {
      "title": "Zimbabwe Dollar",
      "x-country-name": "ZIMBABWE",
      "x-withdrawal-date": "2008-08",
      "const": 716
    },
    {
      "title": "Yemeni Dinar",
      "x-country-name": "YEMEN, DEMOCRATIC",
      "x-withdrawal-date": "1991-09",
      "const": 720
    },
    {
      "title": "Spanish Peseta",
      "x-country-name": "SPAIN",
      "x-withdrawal-date": "2002-03",
      "const": 724
    },
    {
      "title": "Sudanese Pound",
      "x-country-name": "SUDAN",
      "x-withdrawal-date": "1998-06",
      "const": 736
    },
    {
      "title": "Surinam Guilder",
      "x-country-name": "SURINAME",
      "x-withdrawal-date": "2003-12",
      "const": 740
    },
    {
      "title": "Lilangeni",
      "x-country-name": "SWAZILAND",
      "x-withdrawal-date": "2018-08",
      "const": 748
    },
    {
      "title": "Tajik Ruble",
      "x-country-name": "TAJIKISTAN",
      "x-withdrawal-date": "2001-04",
      "const": 762
    },
    {
      "title": "Old Turkish Lira",
      "x-country-name": "TURKEY",
      "x-withdrawal-date": "2005-12",
      "const": 792
    },
    {
      "title": "Turkmenistan Manat",
      "x-country-name": "TURKMENISTAN",
      "x-withdrawal-date": "2009-01",
      "const": 795
    },
    {
      "title": "Old Shilling",
      "x-country-name": "UGANDA",
      "x-withdrawal-date": "1989 to 1990",
      "const": 800
    },
    {
      "title": "Karbovanet",
      "x-country-name": "UKRAINE",
      "x-withdrawal-date": "1996-09",
      "const": 804
    },
    {
      "title": "Russian Ruble",
      "x-country-name": "UZBEKISTAN",
      "x-withdrawal-date": "1994-07",
      "const": 810
    },
    {
      "title": "Uruguayan Peso",
      "x-country-name": "URUGUAY",
      "x-withdrawal-date": "1993-03",
      "const": 858
    },
    {
      "title": "Bolivar",
      "x-country-name": "VENEZUELA",
      "x-withdrawal-date": "2008-01",
      "const": 862
    },
    {
      "title": "Yugoslavian Dinar",
      "x-country-name": "YUGOSLAVIA",
      "x-withdrawal-date": "1995-11",
      "const": 890
    },
    {
      "title": "New Dinar",
      "x-country-name": "YUGOSLAVIA",
      "x-withdrawal-date": "2003-07",
      "const": 891
    },
    {
      "title": "Zambian Kwacha",
      "x-country-name": "ZAMBIA",
      "x-withdrawal-date": "2012-12",
      "const": 894
    },
    {
      "title": "Peso Convertible",
      "x-country-name": "CUBA",
      "x-withdrawal-date": "2021-06",
      "const": 931
    },
    {
      "title": "Zimbabwe Dollar",
      "x-country-name": "ZIMBABWE",
      "x-withdrawal-date": "2024-09",
      "const": 932
    },
    {
      "title": "Zimbabwe Dollar",
      "x-country-name": "ZIMBABWE",
      "x-withdrawal-date": "2009-06",
      "const": 935
    },
    {
      "title": "Bolívar",
      "x-country-name": "VENEZUELA (BOLIVARIAN REPUBLIC OF)",
      "x-withdrawal-date": "2018-08",
      "const": 937
    },
    {
      "title": "Sudanese Pound",
      "x-country-name": "SOUTH SUDAN",
      "x-withdrawal-date": "2012-09",
      "const": 938
    },
    {
      "title": "Ghana Cedi",
      "x-country-name": "GHANA",
      "x-withdrawal-date": "2007-06",
      "const": 939
    },
    {
      "title": "Zimbabwe Dollar (new)",
      "x-country-name": "ZIMBABWE",
      "x-withdrawal-date": "2006-09",
      "const": 942
    },
    {
      "title": "Azerbaijan Manat",
      "x-country-name": "AZERBAIJAN",
      "x-withdrawal-date": "2005-10",
      "const": 945
    },
    {
      "title": "New Romanian Leu",
      "x-country-name": "ROMANIA",
      "x-withdrawal-date": "2015-06",
      "const": 946
    },
    {
      "title": "WIR Franc (for electronic)",
      "x-country-name": "SWITZERLAND",
      "x-withdrawal-date": "2004-11",
      "const": 948
    },
    {
      "title": "New Turkish Lira",
      "x-country-name": "TURKEY",
      "x-withdrawal-date": "2009-01",
      "const": 949
    },
    {
      "title": "European Currency Unit (E.C.U)",
      "x-country-name": "EUROPEAN MONETARY CO-OPERATION FUND (EMCF)",
      "x-withdrawal-date": "1999-01",
      "const": 954
    },
    {
      "title": "Belarusian Ruble",
      "x-country-name": "BELARUS",
      "x-withdrawal-date": "2017-01",
      "const": 974
    },
    {
      "title": "Euro",
      "x-country-name": "SERBIA AND MONTENEGRO",
      "x-withdrawal-date": "2006-10",
      "const": 978
    },
    {
      "title": "Kwanza Reajustado",
      "x-country-name": "ANGOLA",
      "x-withdrawal-date": "2000-02",
      "const": 982
    },
    {
      "title": "Unidad de Valor Constante (UVC)",
      "x-country-name": "ECUADOR",
      "x-withdrawal-date": "2000-09",
      "const": 983
    },
    {
      "title": "Cruzeiro Real",
      "x-country-name": "BRAZIL",
      "x-withdrawal-date": "1994-07",
      "const": 987
    },
    {
      "title": "Luxembourg Financial Franc",
      "x-country-name": "LUXEMBOURG",
      "x-withdrawal-date": "1990-03",
      "const": 988
    },
    {
      "title": "Luxembourg Convertible Franc",
      "x-country-name": "LUXEMBOURG",
      "x-withdrawal-date": "1990-03",
      "const": 989
    },
    {
      "title": "Financial Rand",
      "x-country-name": "SOUTH AFRICA",
      "x-withdrawal-date": "1995-03",
      "const": 991
    },
    {
      "title": "Financial Franc",
      "x-country-name": "BELGIUM",
      "x-withdrawal-date": "1990-03",
      "const": 992
    },
    {
      "title": "Convertible Franc",
      "x-country-name": "BELGIUM",
      "x-withdrawal-date": "1990-03",
      "const": 993
    },
    {
      "title": "\"A\" Account (convertible Peseta Account)",
      "x-country-name": "SPAIN",
      "x-withdrawal-date": "1994-12",
      "const": 995
    },
    {
      "title": "Spanish Peseta",
      "x-country-name": "SPAIN",
      "x-withdrawal-date": "1978 to 1981",
      "const": 996
    },
    {
      "title": "US Dollar (Same day)",
      "x-country-name": "UNITED STATES",
      "x-withdrawal-date": "2014-03",
      "const": 998
    }
  ]
}
